<structure>
<point x="19.25" y="23.98" b="G"/>
<point x="27.22" y="23.98" b="A"/>
<point x="34.78" y="23.98" b="A"/>
<point x="42.13" y="23.98" b="U"/>
<point x="49.48" y="23.98" b="G"/>
<point x="57.46" y="23.98" b="A"/>
<point x="65.02" y="23.98" b="A"/>
<point x="72.17" y="23.98" b="G"/>
<point x="80.14" y="23.98" b="A"/>
<point x="87.50" y="23.98" b="C"/>
<point x="94.84" y="23.98" b="G"/>
<point x="102.61" y="23.98" b="U"/>
<point x="110.17" y="23.98" b="U"/>
<point x="117.73" y="23.98" b="C"/>
<point x="125.30" y="23.98" b="C"/>
<point x="133.06" y="23.98" b="A"/>
<point x="140.41" y="23.98" b="C"/>
<point x="147.97" y="23.98" b="C"/>
<point x="155.53" y="23.98" b="C"/>
<point x="162.88" y="23.98" b="G"/>
<point x="170.86" y="23.98" b="A"/>
<point x="178.00" y="23.98" b="G"/>
<point x="185.78" y="23.98" b="C"/>
<point x="193.12" y="23.98" b="G"/>
<point x="201.10" y="23.98" b="A"/>
<point x="208.25" y="23.98" b="G"/>
<point x="216.01" y="23.98" b="U"/>
<point x="223.37" y="23.98" b="G"/>
<point x="231.34" y="23.98" b="A"/>
<point x="238.69" y="23.98" b="U"/>
<point x="246.04" y="23.98" b="G"/>
<point x="254.02" y="23.98" b="A"/>
<point x="261.17" y="23.98" b="G"/>
<point x="268.94" y="23.98" b="C"/>
<point x="276.29" y="23.98" b="G"/>
<point x="284.26" y="23.98" b="A"/>
<point x="291.82" y="23.98" b="A"/>
<point x="299.38" y="23.98" b="A"/>
<point x="306.74" y="23.98" b="C"/>
<point x="314.08" y="23.98" b="G"/>
<point x="321.64" y="23.98" b="G"/>
<point x="329.42" y="23.98" b="U"/>
<point x="336.98" y="23.98" b="U"/>
<point x="344.74" y="23.98" b="A"/>
<point x="352.30" y="23.98" b="A"/>
<point x="359.65" y="23.98" b="U"/>
<point x="367.42" y="23.98" b="A"/>
<point x="374.77" y="23.98" b="C"/>
<point x="382.33" y="23.98" b="U"/>
<point x="389.69" y="23.98" b="G"/>
<point x="397.66" y="23.98" b="A"/>
<point x="405.01" y="23.98" b="U"/>
<point x="412.37" y="23.98" b="G"/>
</structure>