<structure>
<point x="39.00" y="378.63" b="G"/>
<point x="39.00" y="361.13" b="G"/>
<point x="39.00" y="343.64" b="U"/>
<point x="39.00" y="326.15" b="U"/>
<point x="39.00" y="308.65" b="U"/>
<point x="39.00" y="291.16" b="A"/>
<point x="39.00" y="252.18" b="G"/>
<point x="39.00" y="234.69" b="C"/>
<point x="39.00" y="217.20" b="A"/>
<point x="39.00" y="199.70" b="C"/>
<point x="39.00" y="182.21" b="U"/>
<point x="28.16" y="170.80" b="C"/>
<point x="24.40" y="155.53" b="C"/>
<point x="28.69" y="140.39" b="N"/>
<point x="39.90" y="129.36" b="C"/>
<point x="55.11" y="125.33" b="C"/>
<point x="70.32" y="129.36" b="C"/>
<point x="81.54" y="140.39" b="U"/>
<point x="85.83" y="155.53" b="A"/>
<point x="82.06" y="170.80" b="U"/>
<point x="71.23" y="182.21" b="A"/>
<point x="71.23" y="199.70" b="G"/>
<point x="71.23" y="217.20" b="U"/>
<point x="71.23" y="234.69" b="G"/>
<point x="71.23" y="252.18" b="C"/>
<point x="79.32" y="264.36" b="C"/>
<point x="79.32" y="278.98" b="U"/>
<point x="71.23" y="291.16" b="A"/>
<point x="71.23" y="308.65" b="U"/>
<point x="71.23" y="326.15" b="U"/>
<point x="71.23" y="343.64" b="C"/>
<point x="71.23" y="361.13" b="C"/>
<point x="71.23" y="378.63" b="A"/>
<point x="83.69" y="378.63" b="U"/>
<point x="96.15" y="378.63" b="A"/>
<point x="108.61" y="378.63" b="U"/>
<point x="121.07" y="378.63" b="C"/>
<point x="133.53" y="378.63" b="N"/>
<point x="145.99" y="378.63" b="A"/>
<point x="158.45" y="378.63" b="U"/>
<point x="170.91" y="378.63" b="U"/>
<point x="183.37" y="378.63" b="A"/>
<point x="195.83" y="378.63" b="A"/>
<point x="208.29" y="378.63" b="C"/>
<point x="220.75" y="378.63" b="U"/>
<point x="233.21" y="378.63" b="U"/>
<point x="245.67" y="378.63" b="G"/>
<point x="258.13" y="378.63" b="G"/>
<point x="258.13" y="361.13" b="U"/>
<point x="258.13" y="343.64" b="U"/>
<point x="258.13" y="326.15" b="A"/>
<point x="258.13" y="308.65" b="C"/>
<point x="258.13" y="291.16" b="A"/>
<point x="246.98" y="280.62" b="U"/>
<point x="241.91" y="266.14" b="U"/>
<point x="244.06" y="250.94" b="A"/>
<point x="252.94" y="238.43" b="U"/>
<point x="266.57" y="231.39" b="C"/>
<point x="281.91" y="231.39" b="U"/>
<point x="295.55" y="238.43" b="U"/>
<point x="304.43" y="250.94" b="U"/>
<point x="306.57" y="266.14" b="C"/>
<point x="301.50" y="280.62" b="C"/>
<point x="290.35" y="291.16" b="U"/>
<point x="290.35" y="308.65" b="G"/>
<point x="290.35" y="326.15" b="U"/>
<point x="290.35" y="343.64" b="G"/>
<point x="290.35" y="361.13" b="A"/>
<point x="290.35" y="378.63" b="C"/>
<point x="302.17" y="378.63" b="A"/>
<point x="313.99" y="378.63" b="Y"/>
<point x="325.80" y="378.63" b="U"/>
<point x="337.62" y="378.63" b="U"/>
<point x="349.43" y="378.63" b="U"/>
<point x="361.25" y="378.63" b="G"/>
<point x="361.25" y="361.13" b="C"/>
<point x="361.25" y="343.64" b="C"/>
<point x="361.25" y="326.15" b="C"/>
<point x="361.25" y="308.65" b="C"/>
<point x="350.82" y="296.22" b="U"/>
<point x="348.71" y="280.14" b="U"/>
<point x="355.56" y="265.43" b="N"/>
<point x="369.25" y="256.71" b="C"/>
<point x="385.47" y="256.71" b="G"/>
<point x="399.16" y="265.43" b="U"/>
<point x="406.02" y="280.14" b="U"/>
<point x="403.90" y="296.22" b="U"/>
<point x="393.47" y="308.65" b="G"/>
<point x="393.47" y="326.15" b="G"/>
<point x="393.47" y="343.64" b="G"/>
<point x="393.47" y="361.13" b="G"/>
<point x="393.47" y="378.63" b="C"/>
<point x="405.90" y="378.63" b="U"/>
<point x="418.33" y="378.63" b="U"/>
<point x="430.76" y="378.63" b="U"/>
<point x="443.19" y="378.63" b="U"/>
<point x="455.62" y="378.63" b="U"/>
<point x="468.05" y="378.63" b="U"/>
<point x="480.48" y="378.63" b="U"/>
</structure>
