<structure>
<point x="17.20" y="385.42" b="G"/>
<point x="28.27" y="385.42" b="A"/>
<point x="39.34" y="385.42" b="U"/>
<point x="50.41" y="385.42" b="C"/>
<point x="61.49" y="385.42" b="A"/>
<point x="72.56" y="385.42" b="G"/>
<point x="83.63" y="385.42" b="C"/>
<point x="94.70" y="385.42" b="N"/>
<point x="105.78" y="385.42" b="N"/>
<point x="116.85" y="385.42" b="N"/>
<point x="127.92" y="385.42" b="N"/>
<point x="127.92" y="370.00" b="G"/>
<point x="127.92" y="354.59" b="Y"/>
<point x="127.92" y="339.18" b="N"/>
<point x="127.92" y="323.77" b="R"/>
<point x="127.92" y="308.36" b="G"/>
<point x="127.92" y="292.94" b="G"/>
<point x="127.92" y="233.30" b="G"/>
<point x="127.92" y="217.89" b="Y"/>
<point x="127.92" y="202.48" b="R"/>
<point x="127.92" y="187.06" b="N"/>
<point x="127.92" y="171.65" b="N"/>
<point x="127.92" y="156.24" b="N"/>
<point x="119.89" y="142.86" b="N"/>
<point x="122.42" y="127.47" b="N"/>
<point x="134.32" y="117.38" b="N"/>
<point x="149.92" y="117.38" b="R"/>
<point x="161.81" y="127.47" b="N"/>
<point x="164.34" y="142.86" b="N"/>
<point x="156.31" y="156.24" b="N"/>
<point x="156.31" y="171.65" b="N"/>
<point x="156.31" y="187.06" b="N"/>
<point x="156.31" y="202.48" b="Y"/>
<point x="156.31" y="217.89" b="R"/>
<point x="156.31" y="233.30" b="C"/>
<point x="162.61" y="237.22" b="R"/>
<point x="167.88" y="242.46" b="N"/>
<point x="171.85" y="248.74" b="C"/>
<point x="174.31" y="255.74" b="G"/>
<point x="175.14" y="263.12" b="G"/>
<point x="174.31" y="270.50" b="A"/>
<point x="171.85" y="277.51" b="A"/>
<point x="167.88" y="283.78" b="C"/>
<point x="162.61" y="289.02" b="U"/>
<point x="156.31" y="292.94" b="C"/>
<point x="156.31" y="308.36" b="Y"/>
<point x="156.31" y="323.77" b="Y"/>
<point x="156.31" y="339.18" b="R"/>
<point x="156.31" y="354.59" b="R"/>
<point x="156.31" y="370.00" b="C"/>
<point x="156.31" y="385.42" b="N"/>
<point x="167.57" y="385.42" b="R"/>
<point x="178.83" y="385.42" b="R"/>
<point x="190.09" y="385.42" b="A"/>
<point x="201.34" y="385.42" b="A"/>
<point x="212.60" y="385.42" b="G"/>
<point x="223.86" y="385.42" b="R"/>
<point x="235.12" y="385.42" b="C"/>
<point x="246.38" y="385.42" b="U"/>
<point x="257.64" y="385.42" b="U"/>
<point x="268.89" y="385.42" b="G"/>
<point x="280.15" y="385.42" b="C"/>
<point x="291.41" y="385.42" b="A"/>
<point x="302.67" y="385.42" b="A"/>
<point x="313.93" y="385.42" b="A"/>
<point x="325.19" y="385.42" b="G"/>
<point x="336.44" y="385.42" b="G"/>
<point x="347.70" y="385.42" b="U"/>
<point x="358.96" y="385.42" b="G"/>
<point x="370.22" y="385.42" b="A"/>
<point x="381.48" y="385.42" b="U"/>
<point x="392.74" y="385.42" b="U"/>
<point x="403.99" y="385.42" b="Y"/>
<point x="415.25" y="385.42" b="C"/>
<point x="426.51" y="385.42" b="C"/>
<point x="437.77" y="385.42" b="Y"/>
<point x="449.03" y="385.42" b="U"/>
<point x="460.29" y="385.42" b="U"/>
<point x="471.54" y="385.42" b="U"/>
<point x="482.80" y="385.42" b="C"/>
</structure>
