<structure>
<point x="115.66" y="289.29" b="A"/>
<point x="115.66" y="281.73" b="A"/>
<point x="115.60" y="274.38" b="N"/>
<point x="115.45" y="266.61" b="U"/>
<point x="115.45" y="259.05" b="R"/>
<point x="115.24" y="251.49" b="G"/>
<point x="107.92" y="250.84" b="R"/>
<point x="100.24" y="249.68" b="G"/>
<point x="93.07" y="248.03" b="U"/>
<point x="85.61" y="245.90" b="G"/>
<point x="78.93" y="243.29" b="A"/>
<point x="71.82" y="240.21" b="U"/>
<point x="64.92" y="236.69" b="G"/>
<point x="58.90" y="232.72" b="A"/>
<point x="52.74" y="228.34" b="A"/>
<point x="46.88" y="223.56" b="A"/>
<point x="41.36" y="218.40" b="A"/>
<point x="36.13" y="213.09" b="N"/>
<point x="30.97" y="207.04" b="G"/>
<point x="26.94" y="201.10" b="N"/>
<point x="23.02" y="194.46" b="A"/>
<point x="19.27" y="187.78" b="U"/>
<point x="16.17" y="180.89" b="C"/>
<point x="13.55" y="173.80" b="C"/>
<point x="11.40" y="166.55" b="U"/>
<point x="9.73" y="159.18" b="U"/>
<point x="8.76" y="151.71" b="A"/>
<point x="7.67" y="144.18" b="G"/>
<point x="7.50" y="136.62" b="G"/>
<point x="8.04" y="129.07" b="C"/>
<point x="8.66" y="121.55" b="G"/>
<point x="10.19" y="114.11" b="U"/>
<point x="11.80" y="106.77" b="G"/>
<point x="14.10" y="99.57" b="G"/>
<point x="17.08" y="92.54" b="U"/>
<point x="20.32" y="85.70" b="U"/>
<point x="24.00" y="79.10" b="R"/>
<point x="28.11" y="72.75" b="U"/>
<point x="32.42" y="66.69" b="G"/>
<point x="37.33" y="60.95" b="G"/>
<point x="42.82" y="55.54" b="C"/>
<point x="48.46" y="50.50" b="C"/>
<point x="54.20" y="45.84" b="G"/>
<point x="60.66" y="41.58" b="U"/>
<point x="67.18" y="37.75" b="C"/>
<point x="73.94" y="34.37" b="U"/>
<point x="80.90" y="31.43" b="U"/>
<point x="87.84" y="28.97" b="G"/>
<point x="95.13" y="26.98" b="G"/>
<point x="102.96" y="25.49" b="Y"/>
<point x="110.25" y="24.49" b="C"/>
<point x="118.00" y="23.98" b="A"/>
<point x="125.35" y="23.98" b="C"/>
<point x="132.90" y="24.49" b="C"/>
<point x="140.39" y="25.49" b="U"/>
<point x="147.95" y="27.19" b="N"/>
<point x="155.09" y="28.97" b="U"/>
<point x="162.24" y="31.43" b="R"/>
<point x="169.42" y="34.37" b="Y"/>
<point x="175.97" y="37.75" b="R"/>
<point x="182.49" y="41.58" b="C"/>
<point x="188.88" y="46.05" b="N"/>
<point x="194.84" y="50.71" b="N"/>
<point x="200.47" y="55.75" b="N"/>
<point x="205.81" y="60.95" b="Y"/>
<point x="210.52" y="66.69" b="U"/>
<point x="215.19" y="72.96" b="N"/>
<point x="219.30" y="79.31" b="N"/>
<point x="222.83" y="85.70" b="C"/>
<point x="226.21" y="92.74" b="N"/>
<point x="228.83" y="99.57" b="R"/>
<point x="231.13" y="106.77" b="U"/>
<point x="232.74" y="114.11" b="G"/>
<point x="234.28" y="121.55" b="C"/>
<point x="235.26" y="129.27" b="N"/>
<point x="235.64" y="136.62" b="A"/>
<point x="235.05" y="144.18" b="G"/>
<point x="234.38" y="151.71" b="G"/>
<point x="233.62" y="159.18" b="A"/>
<point x="231.75" y="166.55" b="C"/>
<point x="229.60" y="173.80" b="U"/>
<point x="226.97" y="180.89" b="U"/>
<point x="223.67" y="187.78" b="G"/>
<point x="220.34" y="194.46" b="U"/>
<point x="216.36" y="200.89" b="C"/>
<point x="212.17" y="207.04" b="A"/>
<point x="207.17" y="212.89" b="U"/>
<point x="202.20" y="218.40" b="A"/>
<point x="196.26" y="223.56" b="G"/>
<point x="190.61" y="228.34" b="U"/>
<point x="184.45" y="232.72" b="U"/>
<point x="178.22" y="236.69" b="A"/>
<point x="171.33" y="240.21" b="C"/>
<point x="164.63" y="243.29" b="A"/>
<point x="157.33" y="245.90" b="C"/>
<point x="150.07" y="248.03" b="U"/>
<point x="142.49" y="249.68" b="G"/>
<point x="135.43" y="250.84" b="A"/>
<point x="127.69" y="251.49" b="C"/>
<point x="127.69" y="259.05" b="U"/>
<point x="127.48" y="266.61" b="G"/>
<point x="127.69" y="274.17" b="U"/>
<point x="127.84" y="281.94" b="N"/>
<point x="127.84" y="289.50" b="N"/>
</structure>