<structure>
<point x="19.66" y="271.94" b="Y"/>
<point x="27.16" y="272.15" b="N"/>
<point x="32.36" y="266.60" b="R"/>
<point x="32.36" y="259.04" b="R"/>
<point x="32.36" y="251.48" b="R"/>
<point x="32.51" y="244.12" b="N"/>
<point x="32.51" y="236.56" b="N"/>
<point x="32.15" y="228.80" b="G"/>
<point x="32.15" y="221.24" b="G"/>
<point x="27.92" y="227.35" b="U"/>
<point x="20.93" y="229.69" b="A"/>
<point x="13.74" y="227.35" b="A"/>
<point x="9.09" y="221.24" b="U"/>
<point x="8.88" y="213.68" b="G"/>
<point x="13.74" y="207.56" b="A"/>
<point x="20.73" y="205.22" b="U"/>
<point x="27.71" y="207.56" b="G"/>
<point x="32.57" y="213.68" b="A"/>
<point x="32.57" y="206.12" b="Y"/>
<point x="32.36" y="198.56" b="C"/>
<point x="29.26" y="191.66" b="U"/>
<point x="32.15" y="184.76" b="G"/>
<point x="32.15" y="177.21" b="G"/>
<point x="32.36" y="169.65" b="U"/>
<point x="29.26" y="162.75" b="U"/>
<point x="32.15" y="155.85" b="G"/>
<point x="32.15" y="148.29" b="G"/>
<point x="27.86" y="142.38" b="A"/>
<point x="27.66" y="134.82" b="C"/>
<point x="32.51" y="129.11" b="N"/>
<point x="32.57" y="121.34" b="A"/>
<point x="32.15" y="113.78" b="G"/>
<point x="32.57" y="106.22" b="A"/>
<point x="29.05" y="99.32" b="G"/>
<point x="32.36" y="92.43" b="U"/>
<point x="32.36" y="84.87" b="C"/>
<point x="32.36" y="77.31" b="U"/>
<point x="32.36" y="69.75" b="C"/>
<point x="29.26" y="62.85" b="U"/>
<point x="32.15" y="55.96" b="G"/>
<point x="32.57" y="48.40" b="A"/>
<point x="32.15" y="40.84" b="G"/>
<point x="28.96" y="34.09" b="C"/>
<point x="31.69" y="27.19" b="N"/>
<point x="38.48" y="23.98" b="U"/>
<point x="45.42" y="26.98" b="U"/>
<point x="48.00" y="34.09" b="U"/>
<point x="44.60" y="40.84" b="C"/>
<point x="44.60" y="48.40" b="U"/>
<point x="44.60" y="55.96" b="C"/>
<point x="47.70" y="62.85" b="U"/>
<point x="44.39" y="69.75" b="G"/>
<point x="44.81" y="77.31" b="A"/>
<point x="44.39" y="84.87" b="G"/>
<point x="44.39" y="92.43" b="G"/>
<point x="47.91" y="99.32" b="A"/>
<point x="44.75" y="106.43" b="N"/>
<point x="44.60" y="113.78" b="C"/>
<point x="44.60" y="121.34" b="U"/>
<point x="44.60" y="128.90" b="U"/>
<point x="52.15" y="129.32" b="U"/>
<point x="57.13" y="134.82" b="G"/>
<point x="57.55" y="142.38" b="A"/>
<point x="52.36" y="147.87" b="A"/>
<point x="44.75" y="148.50" b="N"/>
<point x="44.60" y="155.85" b="C"/>
<point x="47.70" y="162.75" b="C"/>
<point x="44.81" y="169.65" b="A"/>
<point x="44.60" y="177.21" b="C"/>
<point x="44.60" y="184.76" b="C"/>
<point x="47.70" y="191.66" b="U"/>
<point x="44.39" y="198.56" b="G"/>
<point x="44.81" y="206.12" b="A"/>
<point x="44.60" y="213.68" b="U"/>
<point x="44.60" y="221.24" b="C"/>
<point x="44.60" y="228.80" b="C"/>
<point x="44.75" y="236.56" b="N"/>
<point x="44.75" y="244.12" b="N"/>
<point x="44.81" y="251.48" b="Y"/>
<point x="44.81" y="259.04" b="Y"/>
<point x="44.81" y="266.60" b="Y"/>
<point x="50.15" y="271.94" b="A"/>
</structure>