<structure>
<point x="75.44" y="1189.0" b="U" />
<point x="76.24" y="1158.76" b="A" />
<point x="75.44" y="1128.52" b="U" />
<point x="75.44" y="1098.28" b="U" />
<point x="45.96" y="1088.56" b="G" />
<point x="30.0" y="1064.0" b="A" />
<point x="30.0" y="1033.76" b="A" />
<point x="47.6" y="1009.16" b="A" />
<point x="75.44" y="999.44" b="U" />
<point x="75.44" y="969.2" b="U" />
<point x="76.24" y="938.96" b="A" />
<point x="74.6" y="908.72" b="G" />
<point x="75.44" y="878.48" b="U" />
<point x="76.24" y="848.24" b="A" />
<point x="74.6" y="818.0" b="G" />
<point x="75.44" y="787.76" b="U" />
<point x="75.44" y="757.52" b="C" />
<point x="75.44" y="727.28" b="U" />
<point x="76.24" y="697.04" b="A" />
<point x="76.24" y="666.8" b="A" />
<point x="75.44" y="636.56" b="U" />
<point x="75.44" y="606.32" b="U" />
<point x="74.6" y="576.08" b="G" />
<point x="74.6" y="545.84" b="G" />
<point x="75.44" y="515.6" b="U" />
<point x="76.24" y="485.36" b="A" />
<point x="75.44" y="455.12" b="U" />
<point x="63.84" y="427.56" b="A" />
<point x="74.6" y="399.96" b="G" />
<point x="75.44" y="369.72" b="C" />
<point x="75.44" y="339.48" b="U" />
<point x="74.6" y="309.24" b="G" />
<point x="76.24" y="279.0" b="A" />
<point x="46.04" y="277.8" b="A" />
<point x="30.44" y="251.4" b="C" />
<point x="46.04" y="225.04" b="A" />
<point x="76.24" y="223.84" b="A" />
<point x="75.44" y="193.6" b="R" />
<point x="76.24" y="163.36" b="A" />
<point x="62.64" y="136.36" b="A" />
<point x="72.96" y="107.92" b="A" />
<point x="99.92" y="95.92" b="R" />
<point x="128.48" y="107.92" b="A" />
<point x="138.6" y="137.16" b="N" />
<point x="124.4" y="163.36" b="U" />
<point x="125.2" y="193.6" b="Y" />
<point x="124.4" y="223.84" b="U" />
<point x="137.6" y="251.4" b="A" />
<point x="125.2" y="279.0" b="Y" />
<point x="124.4" y="309.24" b="C" />
<point x="125.2" y="339.48" b="A" />
<point x="123.56" y="369.72" b="G" />
<point x="125.2" y="399.96" b="Y" />
<point x="137.4" y="428.36" b="N" />
<point x="123.56" y="455.12" b="G" />
<point x="124.4" y="485.36" b="U" />
<point x="125.2" y="515.6" b="A" />
<point x="124.4" y="545.84" b="U" />
<point x="125.2" y="576.08" b="Y" />
<point x="125.2" y="606.32" b="A" />
<point x="125.2" y="636.56" b="A" />
<point x="155.44" y="636.56" b="A" />
<point x="154.64" y="666.8" b="U" />
<point x="124.4" y="666.8" b="U" />
<point x="124.4" y="697.04" b="U" />
<point x="124.4" y="727.28" b="R" />
<point x="123.56" y="757.52" b="G" />
<point x="125.2" y="787.76" b="A" />
<point x="124.4" y="818.0" b="U" />
<point x="124.4" y="848.24" b="U" />
<point x="125.2" y="878.48" b="A" />
<point x="124.4" y="908.72" b="U" />
<point x="124.4" y="938.96" b="U" />
<point x="125.2" y="969.2" b="A" />
<point x="125.2" y="999.44" b="A" />
<point x="147.6" y="1019.76" b="A" />
<point x="155.88" y="1048.84" b="A" />
<point x="147.6" y="1077.96" b="A" />
<point x="123.56" y="1098.28" b="G" />
<point x="125.2" y="1128.52" b="A" />
<point x="124.4" y="1158.76" b="U" />
<point x="124.4" y="1189.0" b="R" />
<point x="146.6" y="1210.4" b="A" />
</structure>