<structure>
<point x="279.28" y="871.68" b="G" />
<point x="280.12" y="841.44" b="C" />
<point x="280.12" y="811.2" b="C" />
<point x="280.96" y="780.96" b="A" />
<point x="250.8" y="777.44" b="N" />
<point x="221.76" y="769.04" b="A" />
<point x="192.68" y="758.28" b="U" />
<point x="164.92" y="744.48" b="G" />
<point x="141.32" y="727.84" b="A" />
<point x="117.24" y="708.52" b="U" />
<point x="95.36" y="686.8" b="G" />
<point x="77.72" y="662.88" b="U" />
<point x="62.52" y="637.92" b="N" />
<point x="49.08" y="609.72" b="U" />
<point x="39.88" y="581.92" b="N" />
<point x="33.32" y="552.4" b="N" />
<point x="30.0" y="522.36" b="N" />
<point x="30.0" y="492.12" b="N" />
<point x="32.72" y="461.24" b="U" />
<point x="39.28" y="431.72" b="U" />
<point x="49.68" y="403.92" b="N" />
<point x="61.08" y="375.72" b="G" />
<point x="77.72" y="349.92" b="R" />
<point x="96.8" y="326.84" b="N" />
<point x="118.04" y="304.28" b="A" />
<point x="141.12" y="285.8" b="N" />
<point x="165.76" y="268.32" b="R" />
<point x="193.28" y="255.36" b="N" />
<point x="220.08" y="243.8" b="G" />
<point x="251.04" y="236.2" b="A" />
<point x="279.28" y="231.88" b="G" />
<point x="280.12" y="201.64" b="C" />
<point x="280.12" y="171.4" b="R" />
<point x="280.12" y="141.16" b="C" />
<point x="278.68" y="110.92" b="U" />
<point x="305.2" y="96.24" b="N" />
<point x="330.56" y="110.92" b="U" />
<point x="328.24" y="141.16" b="G" />
<point x="329.92" y="171.4" b="Y" />
<point x="328.24" y="201.64" b="G" />
<point x="329.08" y="231.88" b="C" />
<point x="359.8" y="227.2" b="A" />
<point x="389.2" y="225.8" b="R" />
<point x="419.96" y="228.48" b="N" />
<point x="448.32" y="232.76" b="G" />
<point x="478.88" y="241.84" b="N" />
<point x="507.12" y="252.36" b="Y" />
<point x="532.08" y="266.68" b="G" />
<point x="558.72" y="283.76" b="A" />
<point x="580.84" y="303.44" b="C" />
<point x="601.56" y="325.44" b="C" />
<point x="619.8" y="349.6" b="C" />
<point x="635.32" y="375.52" b="U" />
<point x="648.8" y="403.0" b="Y" />
<point x="658.4" y="431.68" b="A" />
<point x="664.04" y="461.24" b="U" />
<point x="667.28" y="491.28" b="C" />
<point x="667.28" y="521.52" b="U" />
<point x="664.88" y="551.6" b="A" />
<point x="657.56" y="581.12" b="U" />
<point x="647.96" y="609.8" b="C" />
<point x="636.16" y="637.28" b="A" />
<point x="619.8" y="663.24" b="C" />
<point x="601.56" y="687.36" b="C" />
<point x="580.84" y="709.36" b="C" />
<point x="558.48" y="729.88" b="N" />
<point x="532.92" y="746.12" b="U" />
<point x="505.44" y="760.44" b="G" />
<point x="479.08" y="771.8" b="A" />
<point x="449.16" y="780.04" b="C" />
<point x="419.36" y="785.16" b="U" />
<point x="388.36" y="787.0" b="G" />
<point x="359.8" y="785.6" b="A" />
<point x="329.08" y="780.96" b="U" />
<point x="328.24" y="811.2" b="G" />
<point x="328.24" y="841.44" b="G" />
<point x="329.08" y="871.68" b="C" />
<point x="350.48" y="893.04" b="U" />
</structure>