<structure>
<point x="139.60" y="314.17" b="U"/>
<point x="147.37" y="314.17" b="A"/>
<point x="154.93" y="314.17" b="A"/>
<point x="162.28" y="314.17" b="U"/>
<point x="169.63" y="314.17" b="G"/>
<point x="177.40" y="314.17" b="U"/>
<point x="185.16" y="314.17" b="A"/>
<point x="192.31" y="314.17" b="G"/>
<point x="200.08" y="314.17" b="C"/>
<point x="207.64" y="314.17" b="U"/>
<point x="214.99" y="314.17" b="G"/>
<point x="222.76" y="314.17" b="C"/>
<point x="228.10" y="308.83" b="C"/>
<point x="228.10" y="301.27" b="U"/>
<point x="228.10" y="293.71" b="U"/>
<point x="228.10" y="286.15" b="U"/>
<point x="228.31" y="278.59" b="A"/>
<point x="228.10" y="271.03" b="U"/>
<point x="228.31" y="263.47" b="A"/>
<point x="220.66" y="262.16" b="U"/>
<point x="213.45" y="259.89" b="U"/>
<point x="206.60" y="256.68" b="U"/>
<point x="202.47" y="262.87" b="A"/>
<point x="197.92" y="269.06" b="C"/>
<point x="193.58" y="275.25" b="U"/>
<point x="189.03" y="281.44" b="G"/>
<point x="184.69" y="287.63" b="G"/>
<point x="180.56" y="293.82" b="U"/>
<point x="176.22" y="300.01" b="C"/>
<point x="179.41" y="306.87" b="C"/>
<point x="171.67" y="306.20" b="G"/>
<point x="167.54" y="312.39" b="U"/>
<point x="163.41" y="318.58" b="A"/>
<point x="168.25" y="324.02" b="G"/>
<point x="175.00" y="319.89" b="A"/>
<point x="181.33" y="315.77" b="A"/>
<point x="187.46" y="311.64" b="U"/>
<point x="193.80" y="307.52" b="C"/>
<point x="200.13" y="303.39" b="C"/>
<point x="206.47" y="299.27" b="C"/>
<point x="212.80" y="295.14" b="U"/>
<point x="219.14" y="291.01" b="C"/>
<point x="225.47" y="286.89" b="C"/>
<point x="227.86" y="279.72" b="C"/>
<point x="234.40" y="275.59" b="A"/>
<point x="241.51" y="276.31" b="G"/>
<point x="248.06" y="272.18" b="U"/>
<point x="251.94" y="265.82" b="G"/>
<point x="259.82" y="264.65" b="A"/>
<point x="263.70" y="258.29" b="C"/>
<point x="271.38" y="257.13" b="A"/>
<point x="277.30" y="253.00" b="G"/>
<point x="283.63" y="248.88" b="G"/>
<point x="289.97" y="244.75" b="G"/>
<point x="291.08" y="237.25" b="C"/>
<point x="295.62" y="231.20" b="C"/>
<point x="302.59" y="228.26" b="U"/>
<point x="310.29" y="229.21" b="A"/>
<point x="316.10" y="233.79" b="U"/>
<point x="323.47" y="232.11" b="U"/>
<point x="330.85" y="230.44" b="C"/>
<point x="338.43" y="228.77" b="A"/>
<point x="345.59" y="227.10" b="U"/>
<point x="353.17" y="225.43" b="A"/>
<point x="358.59" y="220.62" b="G"/>
<point x="366.30" y="221.56" b="C"/>
<point x="370.55" y="227.67" b="G"/>
<point x="369.57" y="235.10" b="A"/>
<point x="362.80" y="239.19" b="G"/>
<point x="355.67" y="237.36" b="U"/>
<point x="348.09" y="239.03" b="G"/>
<point x="340.93" y="240.71" b="U"/>
<point x="333.34" y="242.38" b="G"/>
<point x="326.39" y="244.05" b="A"/>
<point x="319.01" y="245.72" b="A"/>
<point x="315.36" y="252.45" b="C"/>
<point x="318.09" y="259.41" b="G"/>
<point x="321.04" y="266.38" b="G"/>
<point x="324.19" y="273.34" b="U"/>
<point x="327.14" y="280.30" b="C"/>
<point x="330.29" y="287.26" b="A"/>
<point x="337.70" y="288.74" b="A"/>
<point x="342.88" y="283.43" b="U"/>
<point x="348.26" y="278.12" b="C"/>
<point x="353.64" y="272.81" b="C"/>
<point x="356.16" y="265.76" b="G"/>
<point x="363.25" y="263.12" b="G"/>
<point x="368.84" y="257.81" b="C"/>
<point x="364.83" y="251.40" b="C"/>
<point x="363.38" y="244.02" b="A"/>
<point x="364.25" y="236.51" b="A"/>
<point x="367.37" y="229.72" b="C"/>
<point x="372.75" y="224.41" b="U"/>
<point x="379.79" y="221.19" b="A"/>
<point x="387.31" y="220.41" b="A"/>
<point x="394.66" y="222.16" b="A"/>
<point x="400.60" y="226.26" b="G"/>
<point x="406.40" y="220.95" b="Y"/>
<point x="411.57" y="215.64" b="U"/>
<point x="416.96" y="210.33" b="U"/>
<point x="415.05" y="203.01" b="U"/>
<point x="422.34" y="205.02" b="C"/>
<point x="427.92" y="199.71" b="A"/>
<point x="433.10" y="194.40" b="U"/>
<point x="438.69" y="189.09" b="A"/>
<point x="441.42" y="182.04" b="A"/>
<point x="448.30" y="179.40" b="U"/>
<point x="453.47" y="174.09" b="G"/>
<point x="458.85" y="168.78" b="G"/>
<point x="451.55" y="167.88" b="U"/>
<point x="447.57" y="161.46" b="C"/>
<point x="450.32" y="154.34" b="A"/>
<point x="457.27" y="151.89" b="U"/>
<point x="463.85" y="155.95" b="A"/>
<point x="464.65" y="163.47" b="A"/>
<point x="469.61" y="158.16" b="G"/>
<point x="474.99" y="152.85" b="G"/>
<point x="480.58" y="147.54" b="C"/>
<point x="483.10" y="140.49" b="G"/>
<point x="490.19" y="137.85" b="G"/>
<point x="490.44" y="130.29" b="C"/>
<point x="494.68" y="124.03" b="U"/>
<point x="501.47" y="121.18" b="G"/>
<point x="509.29" y="122.70" b="A"/>
<point x="514.39" y="128.08" b="C"/>
<point x="515.82" y="135.51" b="C"/>
<point x="512.87" y="142.47" b="R"/>
<point x="506.76" y="146.62" b="A"/>
<point x="499.00" y="146.56" b="C"/>
<point x="496.06" y="153.61" b="G"/>
<point x="488.97" y="156.25" b="G"/>
<point x="483.80" y="161.56" b="U"/>
<point x="478.42" y="166.87" b="C"/>
<point x="473.04" y="172.18" b="U"/>
<point x="467.66" y="177.49" b="C"/>
<point x="462.27" y="182.80" b="C"/>
<point x="457.10" y="188.11" b="A"/>
<point x="454.16" y="195.16" b="C"/>
<point x="447.08" y="197.80" b="U"/>
<point x="441.49" y="203.11" b="G"/>
<point x="436.31" y="208.42" b="U"/>
<point x="430.72" y="213.73" b="G"/>
<point x="425.76" y="219.04" b="A"/>
<point x="420.38" y="224.35" b="A"/>
<point x="414.58" y="229.66" b="G"/>
<point x="409.41" y="234.97" b="C"/>
<point x="412.21" y="242.07" b="A"/>
<point x="412.18" y="249.63" b="C"/>
<point x="410.13" y="256.85" b="A"/>
<point x="405.68" y="262.96" b="A"/>
<point x="399.51" y="267.32" b="A"/>
<point x="392.06" y="269.48" b="U"/>
<point x="384.71" y="269.20" b="A"/>
<point x="377.23" y="266.52" b="G"/>
<point x="372.05" y="271.83" b="C"/>
<point x="369.11" y="278.88" b="G"/>
<point x="362.03" y="281.52" b="G"/>
<point x="356.65" y="286.83" b="G"/>
<point x="351.68" y="292.14" b="A"/>
<point x="346.10" y="297.45" b="U"/>
<point x="347.26" y="304.88" b="G"/>
<point x="345.46" y="312.17" b="U"/>
<point x="340.48" y="317.86" b="C"/>
<point x="333.31" y="320.80" b="G"/>
<point x="325.97" y="320.42" b="U"/>
<point x="319.34" y="316.78" b="C"/>
<point x="314.96" y="310.62" b="U"/>
<point x="307.19" y="310.78" b="G"/>
<point x="299.85" y="310.94" b="U"/>
<point x="292.29" y="311.10" b="U"/>
<point x="284.52" y="311.26" b="G"/>
<point x="276.96" y="311.43" b="G"/>
<point x="269.40" y="311.59" b="G"/>
<point x="262.06" y="311.75" b="C"/>
<point x="254.50" y="311.92" b="C"/>
<point x="246.73" y="312.08" b="G"/>
<point x="239.59" y="312.24" b="A"/>
<point x="233.36" y="317.07" b="G"/>
<point x="226.21" y="317.23" b="A"/>
<point x="220.20" y="312.66" b="A"/>
<point x="212.43" y="312.82" b="U"/>
<point x="204.66" y="312.98" b="G"/>
<point x="197.32" y="313.14" b="C"/>
<point x="189.55" y="313.31" b="G"/>
<point x="181.99" y="313.47" b="G"/>
<point x="174.43" y="313.63" b="G"/>
<point x="167.08" y="313.79" b="C"/>
<point x="163.47" y="320.43" b="C"/>
<point x="167.63" y="326.87" b="A"/>
<point x="171.59" y="333.31" b="A"/>
<point x="175.13" y="339.75" b="G"/>
<point x="179.30" y="346.20" b="C"/>
<point x="183.46" y="352.64" b="A"/>
<point x="190.53" y="351.62" b="G"/>
<point x="198.18" y="352.97" b="C"/>
<point x="202.21" y="346.71" b="G"/>
<point x="206.46" y="340.46" b="G"/>
<point x="210.70" y="334.20" b="G"/>
<point x="215.15" y="327.94" b="U"/>
<point x="219.39" y="321.69" b="U"/>
<point x="213.10" y="317.20" b="G"/>
<point x="214.16" y="309.67" b="A"/>
<point x="220.92" y="306.28" b="A"/>
<point x="226.92" y="310.27" b="G"/>
<point x="231.37" y="304.01" b="C"/>
<point x="235.41" y="297.75" b="G"/>
<point x="236.80" y="290.26" b="A"/>
<point x="242.71" y="285.82" b="U"/>
<point x="250.14" y="287.24" b="U"/>
<point x="254.20" y="293.61" b="U"/>
<point x="252.56" y="300.94" b="A"/>
<point x="245.75" y="304.62" b="C"/>
<point x="241.29" y="310.88" b="G"/>
<point x="237.26" y="317.14" b="C"/>
<point x="236.16" y="324.58" b="A"/>
<point x="229.73" y="328.55" b="A"/>
<point x="225.49" y="334.81" b="A"/>
<point x="221.04" y="341.07" b="U"/>
<point x="216.80" y="347.33" b="C"/>
<point x="212.56" y="353.58" b="C"/>
<point x="208.10" y="359.84" b="G"/>
<point x="212.12" y="366.25" b="G"/>
<point x="214.15" y="373.58" b="C"/>
<point x="213.60" y="381.12" b="U"/>
<point x="210.95" y="388.12" b="A"/>
<point x="205.85" y="393.88" b="C"/>
<point x="209.15" y="400.69" b="C"/>
<point x="212.24" y="407.49" b="G"/>
<point x="217.56" y="413.06" b="C"/>
<point x="216.35" y="420.49" b="A"/>
<point x="209.55" y="423.78" b="A"/>
<point x="202.64" y="420.29" b="U"/>
<point x="201.43" y="412.83" b="C"/>
<point x="197.93" y="406.03" b="G"/>
<point x="194.63" y="399.23" b="G"/>
<point x="187.07" y="399.50" b="G"/>
<point x="180.22" y="397.41" b="A"/>
<point x="173.97" y="393.17" b="A"/>
<point x="169.34" y="387.19" b="A"/>
<point x="166.79" y="380.07" b="A"/>
<point x="166.17" y="372.51" b="G"/>
<point x="168.74" y="365.27" b="A"/>
<point x="172.82" y="359.05" b="U"/>
<point x="168.66" y="352.60" b="G"/>
<point x="164.91" y="346.16" b="C"/>
<point x="160.95" y="339.72" b="U"/>
<point x="156.99" y="333.28" b="U"/>
<point x="152.83" y="326.84" b="G"/>
<point x="145.48" y="327.07" b="U"/>
<point x="141.71" y="333.74" b="G"/>
<point x="138.36" y="340.41" b="C"/>
<point x="134.80" y="347.08" b="C"/>
<point x="131.03" y="353.75" b="G"/>
<point x="127.68" y="360.41" b="U"/>
<point x="133.38" y="365.38" b="U"/>
<point x="138.15" y="371.24" b="U"/>
<point x="141.84" y="377.84" b="U"/>
<point x="144.35" y="384.97" b="C"/>
<point x="145.39" y="392.43" b="G"/>
<point x="145.55" y="399.99" b="U"/>
<point x="144.21" y="407.43" b="C"/>
<point x="141.82" y="414.53" b="A"/>
<point x="137.63" y="421.08" b="G"/>
<point x="132.99" y="426.88" b="C"/>
<point x="127.23" y="431.77" b="C"/>
<point x="120.92" y="435.61" b="A"/>
<point x="113.63" y="438.26" b="C"/>
<point x="114.64" y="445.76" b="U"/>
<point x="115.64" y="453.25" b="C"/>
<point x="121.45" y="457.83" b="G"/>
<point x="124.11" y="464.98" b="C"/>
<point x="122.39" y="472.29" b="A"/>
<point x="116.30" y="477.29" b="G"/>
<point x="109.22" y="478.29" b="A"/>
<point x="102.02" y="474.96" b="G"/>
<point x="98.44" y="468.43" b="C"/>
<point x="99.12" y="460.88" b="A"/>
<point x="103.30" y="454.88" b="G"/>
<point x="102.71" y="447.38" b="A"/>
<point x="101.29" y="439.89" b="G"/>
<point x="93.97" y="439.19" b="C"/>
<point x="86.88" y="437.22" b="A"/>
<point x="80.03" y="434.02" b="A"/>
<point x="73.83" y="429.69" b="A"/>
<point x="68.26" y="424.37" b="U"/>
<point x="63.88" y="418.21" b="U"/>
<point x="60.83" y="411.38" b="A"/>
<point x="58.79" y="404.10" b="A"/>
<point x="57.62" y="396.58" b="G"/>
<point x="50.32" y="395.64" b="C"/>
<point x="42.82" y="394.70" b="U"/>
<point x="35.49" y="394.12" b="A"/>
<point x="32.44" y="387.20" b="A"/>
<point x="36.90" y="381.25" b="C"/>
<point x="44.55" y="382.55" b="A"/>
<point x="51.64" y="383.50" b="G"/>
<point x="59.35" y="384.44" b="C"/>
<point x="61.95" y="377.34" b="C"/>
<point x="65.51" y="370.79" b="G"/>
<point x="60.39" y="365.64" b="A"/>
<point x="54.44" y="360.50" b="G"/>
<point x="49.11" y="355.35" b="C"/>
<point x="43.77" y="350.20" b="A"/>
<point x="37.82" y="345.06" b="G"/>
<point x="32.49" y="339.91" b="C"/>
<point x="25.91" y="336.58" b="A"/>
<point x="24.54" y="329.14" b="A"/>
<point x="29.69" y="323.60" b="A"/>
<point x="37.00" y="324.43" b="C"/>
<point x="40.61" y="330.95" b="G"/>
<point x="46.36" y="336.09" b="C"/>
<point x="51.90" y="341.24" b="U"/>
<point x="57.23" y="346.38" b="G"/>
<point x="62.98" y="351.53" b="U"/>
<point x="68.52" y="356.68" b="U"/>
<point x="74.05" y="361.82" b="C"/>
<point x="80.31" y="357.57" b="U"/>
<point x="87.20" y="354.46" b="C"/>
<point x="94.52" y="352.58" b="C"/>
<point x="101.85" y="351.98" b="G"/>
<point x="109.58" y="352.67" b="U"/>
<point x="117.09" y="354.65" b="A"/>
<point x="120.44" y="347.98" b="C"/>
<point x="123.79" y="341.31" b="G"/>
<point x="127.35" y="334.64" b="G"/>
<point x="131.12" y="327.97" b="C"/>
<point x="134.89" y="321.30" b="A"/>
<point x="130.46" y="314.90" b="G"/>
<point x="129.63" y="307.44" b="A"/>
<point x="131.36" y="300.08" b="A"/>
<point x="135.57" y="293.95" b="C"/>
<point x="142.01" y="289.99" b="U"/>
<point x="149.48" y="288.81" b="C"/>
<point x="156.83" y="290.60" b="C"/>
<point x="163.13" y="295.08" b="A"/>
<point x="166.61" y="301.56" b="G"/>
<point x="174.38" y="301.39" b="C"/>
<point x="181.94" y="301.23" b="C"/>
<point x="189.50" y="301.07" b="C"/>
<point x="196.84" y="300.91" b="G"/>
<point x="204.61" y="300.74" b="U"/>
<point x="212.38" y="300.58" b="A"/>
<point x="219.73" y="300.42" b="U"/>
<point x="225.33" y="295.59" b="G"/>
<point x="233.31" y="295.43" b="A"/>
<point x="239.12" y="300.00" b="U"/>
<point x="246.68" y="299.84" b="C"/>
<point x="254.02" y="299.68" b="G"/>
<point x="261.58" y="299.51" b="G"/>
<point x="269.35" y="299.35" b="C"/>
<point x="276.91" y="299.19" b="C"/>
<point x="284.47" y="299.03" b="U"/>
<point x="292.23" y="298.87" b="A"/>
<point x="299.79" y="298.70" b="A"/>
<point x="307.14" y="298.54" b="C"/>
<point x="314.49" y="298.38" b="G"/>
<point x="318.81" y="292.03" b="U"/>
<point x="315.65" y="285.07" b="G"/>
<point x="313.13" y="278.11" b="A"/>
<point x="309.98" y="271.14" b="C"/>
<point x="307.03" y="264.18" b="C"/>
<point x="303.88" y="257.22" b="G"/>
<point x="296.86" y="255.01" b="C"/>
<point x="290.52" y="259.13" b="C"/>
<point x="284.19" y="263.26" b="C"/>
<point x="277.85" y="267.38" b="U"/>
<point x="273.97" y="273.75" b="A"/>
<point x="266.29" y="274.91" b="U"/>
<point x="262.00" y="281.27" b="G"/>
<point x="254.53" y="282.44" b="G"/>
<point x="248.40" y="286.56" b="C"/>
<point x="246.22" y="293.73" b="A"/>
<point x="239.88" y="297.86" b="A"/>
<point x="231.94" y="297.15" b="G"/>
<point x="225.61" y="301.27" b="G"/>
<point x="219.69" y="305.40" b="A"/>
<point x="219.89" y="312.95" b="C"/>
<point x="212.94" y="309.52" b="G"/>
<point x="206.60" y="313.65" b="G"/>
<point x="200.27" y="317.77" b="G"/>
<point x="194.35" y="321.90" b="A"/>
<point x="187.81" y="326.02" b="U"/>
<point x="181.47" y="330.15" b="U"/>
<point x="175.14" y="334.28" b="C"/>
<point x="177.98" y="341.28" b="U"/>
<point x="185.19" y="339.81" b="G"/>
<point x="192.82" y="338.35" b="C"/>
<point x="200.23" y="336.88" b="C"/>
<point x="207.65" y="335.42" b="U"/>
<point x="215.19" y="333.59" b="A"/>
<point x="220.06" y="339.20" b="U"/>
<point x="217.50" y="346.32" b="C"/>
<point x="210.23" y="347.42" b="A"/>
<point x="202.40" y="348.89" b="G"/>
<point x="194.98" y="350.36" b="G"/>
<point x="187.77" y="351.82" b="C"/>
<point x="180.56" y="353.29" b="A"/>
<point x="180.39" y="360.85" b="U"/>
<point x="179.11" y="368.33" b="G"/>
<point x="177.38" y="375.58" b="A"/>
<point x="174.21" y="382.44" b="A"/>
<point x="169.87" y="388.77" b="C"/>
<point x="164.86" y="394.43" b="U"/>
<point x="159.28" y="399.30" b="A"/>
<point x="152.86" y="403.29" b="A"/>
<point x="145.50" y="406.29" b="G"/>
<point x="150.23" y="412.35" b="C"/>
<point x="148.48" y="419.76" b="G"/>
<point x="150.12" y="427.14" b="G"/>
<point x="151.96" y="434.52" b="U"/>
<point x="153.59" y="441.90" b="C"/>
<point x="155.02" y="449.28" b="G"/>
<point x="156.86" y="456.66" b="C"/>
<point x="158.64" y="463.96" b="G"/>
<point x="153.36" y="469.15" b="U"/>
<point x="146.39" y="466.76" b="A"/>
<point x="144.70" y="459.31" b="G"/>
<point x="143.28" y="451.93" b="C"/>
<point x="141.43" y="444.55" b="G"/>
<point x="139.80" y="437.16" b="G"/>
<point x="138.38" y="429.78" b="C"/>
<point x="136.74" y="422.40" b="C"/>
<point x="132.43" y="416.34" b="A"/>
<point x="133.76" y="408.94" b="C"/>
<point x="126.20" y="409.14" b="C"/>
<point x="118.70" y="408.24" b="U"/>
<point x="111.40" y="406.26" b="C"/>
<point x="104.47" y="403.25" b="C"/>
<point x="98.05" y="399.25" b="C"/>
<point x="92.91" y="404.80" b="C"/>
<point x="95.35" y="412.02" b="A"/>
<point x="87.77" y="410.34" b="U"/>
<point x="82.64" y="415.89" b="U"/>
<point x="77.50" y="421.44" b="U"/>
<point x="75.29" y="428.60" b="A"/>
<point x="68.12" y="431.55" b="U"/>
<point x="62.99" y="437.10" b="U"/>
<point x="57.64" y="442.64" b="G"/>
<point x="52.71" y="448.19" b="C"/>
<point x="47.78" y="453.73" b="A"/>
<point x="42.64" y="459.28" b="A"/>
<point x="37.29" y="464.82" b="U"/>
<point x="32.16" y="470.37" b="U"/>
<point x="26.81" y="475.91" b="G"/>
<point x="21.88" y="481.46" b="C"/>
<point x="17.01" y="487.25" b="U"/>
<point x="9.62" y="485.69" b="U"/>
<point x="7.50" y="478.43" b="C"/>
<point x="12.69" y="473.14" b="G"/>
<point x="18.04" y="467.59" b="C"/>
<point x="23.38" y="462.05" b="A"/>
<point x="28.52" y="456.50" b="A"/>
<point x="33.45" y="450.96" b="U"/>
<point x="38.59" y="445.41" b="U"/>
<point x="43.52" y="439.87" b="G"/>
<point x="48.87" y="434.32" b="U"/>
<point x="54.21" y="428.78" b="A"/>
<point x="59.35" y="423.23" b="A"/>
<point x="61.76" y="416.07" b="A"/>
<point x="68.72" y="413.12" b="A"/>
<point x="73.86" y="407.57" b="A"/>
<point x="79.00" y="402.02" b="A"/>
<point x="83.72" y="396.48" b="G"/>
<point x="89.22" y="391.14" b="N"/>
<point x="84.60" y="384.84" b="U"/>
<point x="81.07" y="378.15" b="U"/>
<point x="78.75" y="371.03" b="A"/>
<point x="77.28" y="363.61" b="A"/>
<point x="76.70" y="356.06" b="C"/>
<point x="77.43" y="348.54" b="U"/>
<point x="79.45" y="341.20" b="A"/>
<point x="82.10" y="334.20" b="U"/>
<point x="85.94" y="327.69" b="C"/>
<point x="90.69" y="321.81" b="C"/>
<point x="96.45" y="316.68" b="A"/>
<point x="102.49" y="312.41" b="C"/>
<point x="109.49" y="309.10" b="A"/>
<point x="116.49" y="306.80" b="U"/>
<point x="123.95" y="305.58" b="U"/>
<point x="131.50" y="305.45" b="U"/>
<point x="138.79" y="306.42" b="G"/>
<point x="146.49" y="308.47" b="A"/>
<point x="153.18" y="311.56" b="U"/>
<point x="157.73" y="305.37" b="A"/>
<point x="161.86" y="299.18" b="C"/>
<point x="165.99" y="292.99" b="G"/>
<point x="170.75" y="286.80" b="A"/>
<point x="174.88" y="280.61" b="C"/>
<point x="179.22" y="274.42" b="U"/>
<point x="183.77" y="268.23" b="A"/>
<point x="187.69" y="262.04" b="G"/>
<point x="192.24" y="255.84" b="U"/>
<point x="196.79" y="249.66" b="A"/>
<point x="191.23" y="244.31" b="C"/>
<point x="186.63" y="238.31" b="U"/>
<point x="182.87" y="231.75" b="U"/>
<point x="180.00" y="224.76" b="U"/>
<point x="178.08" y="217.45" b="U"/>
<point x="177.15" y="209.94" b="U"/>
<point x="177.00" y="202.38" b="G"/>
<point x="178.26" y="194.90" b="C"/>
<point x="180.30" y="187.62" b="C"/>
<point x="183.28" y="180.67" b="C"/>
<point x="187.35" y="174.18" b="A"/>
<point x="191.84" y="168.25" b="U"/>
<point x="197.27" y="162.99" b="C"/>
<point x="203.35" y="158.50" b="C"/>
<point x="210.18" y="154.84" b="A"/>
<point x="217.01" y="152.10" b="U"/>
<point x="224.36" y="150.30" b="U"/>
<point x="231.88" y="149.50" b="U"/>
<point x="239.58" y="149.89" b="N"/>
<point x="246.90" y="150.87" b="U"/>
<point x="254.15" y="153.03" b="R"/>
<point x="261.25" y="156.13" b="A"/>
<point x="267.47" y="160.11" b="C"/>
<point x="272.50" y="154.46" b="U"/>
<point x="277.53" y="148.82" b="C"/>
<point x="282.35" y="143.17" b="G"/>
<point x="287.58" y="137.53" b="U"/>
<point x="289.65" y="130.32" b="G"/>
<point x="296.96" y="127.23" b="A"/>
<point x="301.99" y="121.58" b="A"/>
<point x="306.82" y="115.94" b="U"/>
<point x="302.88" y="109.48" b="U"/>
<point x="300.49" y="102.31" b="U"/>
<point x="299.76" y="94.79" b="U"/>
<point x="300.74" y="87.29" b="U"/>
<point x="303.36" y="80.20" b="U"/>
<point x="307.71" y="73.88" b="A"/>
<point x="313.16" y="68.64" b="A"/>
<point x="319.44" y="64.75" b="C"/>
<point x="326.83" y="62.41" b="A"/>
<point x="334.16" y="61.74" b="U"/>
<point x="335.50" y="54.34" b="G"/>
<point x="337.26" y="46.94" b="U"/>
<point x="332.90" y="40.61" b="G"/>
<point x="333.39" y="33.05" b="A"/>
<point x="337.65" y="26.81" b="A"/>
<point x="344.46" y="23.98" b="U"/>
<point x="351.86" y="25.54" b="U"/>
<point x="357.15" y="30.94" b="U"/>
<point x="358.54" y="38.37" b="U"/>
<point x="355.36" y="45.32" b="G"/>
<point x="349.44" y="49.45" b="A"/>
<point x="347.69" y="56.85" b="C"/>
<point x="346.34" y="64.25" b="A"/>
<point x="352.97" y="67.89" b="A"/>
<point x="358.41" y="72.92" b="U"/>
<point x="362.79" y="79.08" b="C"/>
<point x="365.68" y="86.06" b="U"/>
<point x="366.93" y="93.52" b="U"/>
<point x="366.49" y="101.07" b="C"/>
<point x="364.37" y="108.32" b="U"/>
<point x="360.68" y="114.92" b="C"/>
<point x="355.61" y="120.53" b="C"/>
<point x="349.21" y="124.87" b="G"/>
<point x="351.76" y="132.06" b="U"/>
<point x="353.89" y="139.24" b="G"/>
<point x="356.23" y="146.43" b="G"/>
<point x="358.99" y="153.62" b="A"/>
<point x="361.32" y="160.81" b="A"/>
<point x="363.25" y="168.00" b="G"/>
<point x="365.80" y="175.19" b="C"/>
<point x="373.44" y="176.56" b="A"/>
<point x="379.63" y="180.58" b="C"/>
<point x="384.10" y="186.68" b="C"/>
<point x="386.01" y="194.00" b="U"/>
<point x="385.08" y="201.50" b="C"/>
<point x="381.45" y="208.13" b="C"/>
<point x="375.63" y="212.96" b="U"/>
<point x="368.44" y="215.30" b="C"/>
<point x="360.90" y="214.82" b="U"/>
<point x="354.06" y="211.60" b="U"/>
<point x="348.89" y="206.08" b="C"/>
<point x="346.33" y="199.04" b="A"/>
<point x="346.15" y="191.48" b="U"/>
<point x="348.96" y="184.46" b="C"/>
<point x="353.95" y="178.98" b="G"/>
<point x="351.82" y="171.79" b="C"/>
<point x="349.48" y="164.60" b="U"/>
<point x="347.14" y="157.41" b="U"/>
<point x="344.80" y="150.22" b="C"/>
<point x="342.46" y="143.03" b="C"/>
<point x="340.33" y="135.84" b="A"/>
<point x="337.78" y="128.66" b="U"/>
<point x="330.22" y="128.80" b="U"/>
<point x="322.82" y="127.25" b="C"/>
<point x="316.16" y="124.08" b="A"/>
<point x="310.93" y="129.73" b="U"/>
<point x="305.90" y="135.37" b="U"/>
<point x="303.83" y="142.58" b="A"/>
<point x="296.93" y="145.67" b="A"/>
<point x="291.69" y="151.31" b="C"/>
<point x="286.46" y="156.96" b="G"/>
<point x="281.84" y="162.60" b="A"/>
<point x="276.40" y="168.25" b="G"/>
<point x="281.51" y="174.18" b="A"/>
<point x="284.96" y="180.67" b="G"/>
<point x="288.15" y="187.62" b="C"/>
<point x="290.19" y="194.90" b="C"/>
<point x="291.45" y="202.38" b="A"/>
<point x="291.30" y="209.94" b="C"/>
<point x="290.37" y="217.45" b="C"/>
<point x="288.45" y="224.76" b="U"/>
<point x="285.37" y="231.75" b="G"/>
<point x="291.98" y="235.78" b="C"/>
<point x="298.37" y="239.82" b="C"/>
<point x="304.77" y="243.85" b="C"/>
<point x="311.16" y="247.88" b="C"/>
<point x="317.56" y="251.91" b="U"/>
<point x="323.74" y="255.94" b="G"/>
<point x="330.35" y="259.97" b="C"/>
<point x="336.54" y="264.00" b="G"/>
<point x="343.14" y="268.03" b="C"/>
<point x="350.43" y="270.06" b="U"/>
<point x="353.36" y="277.11" b="A"/>
<point x="349.12" y="283.50" b="U"/>
<point x="341.58" y="284.09" b="U"/>
<point x="336.40" y="278.39" b="G"/>
<point x="330.22" y="274.36" b="C"/>
<point x="323.61" y="270.33" b="G"/>
<point x="317.43" y="266.30" b="C"/>
<point x="311.24" y="262.26" b="A"/>
<point x="304.43" y="258.23" b="G"/>
<point x="298.03" y="254.20" b="G"/>
<point x="291.63" y="250.17" b="G"/>
<point x="285.24" y="246.14" b="G"/>
<point x="279.05" y="242.11" b="C"/>
<point x="273.98" y="247.71" b="U"/>
<point x="268.21" y="252.60" b="U"/>
<point x="261.85" y="256.68" b="U"/>
<point x="255.00" y="259.89" b="U"/>
<point x="247.79" y="262.16" b="U"/>
<point x="240.34" y="263.47" b="U"/>
<point x="240.13" y="271.03" b="G"/>
<point x="240.34" y="278.59" b="U"/>
<point x="240.55" y="286.15" b="A"/>
<point x="240.13" y="293.71" b="G"/>
<point x="240.55" y="301.27" b="A"/>
<point x="240.13" y="308.83" b="G"/>
<point x="245.69" y="314.17" b="C"/>
</structure>