<structure>
<point x="171.60" y="481.12" b="G"/>
<point x="171.60" y="464.20" b="N"/>
<point x="171.60" y="447.27" b="U"/>
<point x="171.60" y="430.35" b="G"/>
<point x="171.60" y="413.43" b="C"/>
<point x="171.60" y="396.51" b="C"/>
<point x="171.60" y="379.58" b="Y"/>
<point x="168.22" y="378.44" b="U"/>
<point x="164.92" y="377.07" b="U"/>
<point x="161.72" y="375.49" b="G"/>
<point x="149.76" y="387.46" b="A"/>
<point x="137.79" y="399.42" b="R"/>
<point x="125.83" y="411.39" b="N"/>
<point x="113.86" y="423.36" b="N"/>
<point x="101.89" y="435.32" b="Y"/>
<point x="100.52" y="450.96" b="N"/>
<point x="90.97" y="463.41" b="N"/>
<point x="76.22" y="468.78" b="C"/>
<point x="60.89" y="465.38" b="U"/>
<point x="49.79" y="454.28" b="C"/>
<point x="46.40" y="438.96" b="C"/>
<point x="51.76" y="424.21" b="U"/>
<point x="64.21" y="414.65" b="N"/>
<point x="79.85" y="413.28" b="G"/>
<point x="91.82" y="401.31" b="N"/>
<point x="103.78" y="389.35" b="N"/>
<point x="115.75" y="377.38" b="Y"/>
<point x="127.72" y="365.42" b="U"/>
<point x="139.68" y="353.45" b="C"/>
<point x="137.93" y="349.87" b="U"/>
<point x="136.45" y="346.17" b="U"/>
<point x="135.24" y="342.38" b="C"/>
<point x="134.32" y="338.50" b="G"/>
<point x="133.69" y="334.57" b="G"/>
<point x="133.35" y="330.60" b="A"/>
<point x="133.30" y="326.62" b="A"/>
<point x="133.55" y="322.64" b="G"/>
<point x="117.92" y="316.16" b="R"/>
<point x="102.28" y="309.69" b="N"/>
<point x="86.65" y="303.21" b="C"/>
<point x="71.02" y="296.74" b="N"/>
<point x="55.38" y="290.26" b="N"/>
<point x="35.70" y="288.69" b="U"/>
<point x="25.36" y="271.87" b="N"/>
<point x="32.83" y="253.60" b="N"/>
<point x="52.00" y="248.86" b="G"/>
<point x="67.31" y="261.46" b="N"/>
<point x="82.94" y="267.94" b="N"/>
<point x="98.58" y="274.41" b="G"/>
<point x="114.21" y="280.89" b="N"/>
<point x="129.85" y="287.36" b="Y"/>
<point x="145.48" y="293.84" b="C"/>
<point x="152.98" y="286.33" b="G"/>
<point x="161.80" y="280.44" b="U"/>
<point x="171.60" y="276.39" b="G"/>
<point x="171.60" y="259.47" b="C"/>
<point x="171.60" y="242.54" b="A"/>
<point x="171.60" y="225.62" b="N"/>
<point x="171.60" y="176.01" b="N"/>
<point x="171.60" y="159.08" b="N"/>
<point x="171.60" y="142.16" b="N"/>
<point x="171.60" y="125.24" b="N"/>
<point x="171.60" y="108.32" b="N"/>
<point x="171.60" y="91.39" b="Y"/>
<point x="171.60" y="74.47" b="N"/>
<point x="171.60" y="57.55" b="C"/>
<point x="168.51" y="35.58" b="A"/>
<point x="187.19" y="23.60" b="N"/>
<point x="205.86" y="35.58" b="R"/>
<point x="202.77" y="57.55" b="R"/>
<point x="202.77" y="74.47" b="N"/>
<point x="202.77" y="91.39" b="R"/>
<point x="202.77" y="108.32" b="N"/>
<point x="202.77" y="125.24" b="N"/>
<point x="202.77" y="142.16" b="N"/>
<point x="202.77" y="159.08" b="N"/>
<point x="202.77" y="176.01" b="Y"/>
<point x="210.09" y="182.55" b="N"/>
<point x="214.84" y="191.14" b="N"/>
<point x="216.48" y="200.81" b="A"/>
<point x="214.84" y="210.49" b="G"/>
<point x="210.09" y="219.08" b="R"/>
<point x="202.77" y="225.62" b="N"/>
<point x="202.77" y="242.54" b="U"/>
<point x="202.77" y="259.47" b="G"/>
<point x="202.77" y="276.39" b="C"/>
<point x="202.77" y="379.58" b="G"/>
<point x="202.77" y="396.51" b="G"/>
<point x="202.77" y="413.43" b="G"/>
<point x="202.77" y="430.35" b="Y"/>
<point x="202.77" y="447.27" b="A"/>
<point x="202.77" y="464.20" b="N"/>
<point x="202.77" y="481.12" b="C"/>
<point x="275.99" y="481.12" b="N"/>
<point x="275.99" y="464.20" b="N"/>
<point x="275.99" y="447.27" b="C"/>
<point x="275.99" y="430.35" b="N"/>
<point x="275.99" y="413.43" b="N"/>
<point x="275.99" y="396.51" b="N"/>
<point x="275.99" y="379.58" b="N"/>
<point x="275.99" y="362.66" b="N"/>
<point x="275.99" y="345.74" b="N"/>
<point x="269.96" y="326.85" b="N"/>
<point x="281.66" y="310.83" b="N"/>
<point x="301.49" y="310.83" b="N"/>
<point x="313.19" y="326.85" b="N"/>
<point x="307.16" y="345.74" b="N"/>
<point x="307.16" y="362.66" b="N"/>
<point x="307.16" y="379.58" b="N"/>
<point x="307.16" y="396.51" b="N"/>
<point x="307.16" y="413.43" b="N"/>
<point x="307.16" y="430.35" b="N"/>
<point x="307.16" y="447.27" b="G"/>
<point x="307.16" y="464.20" b="N"/>
<point x="307.16" y="481.12" b="N"/>
<point x="319.41" y="481.12" b="N"/>
<point x="331.65" y="481.12" b="N"/>
<point x="343.90" y="481.12" b="U"/>
<point x="356.15" y="481.12" b="C"/>
<point x="368.39" y="481.12" b="Y"/>
<point x="380.64" y="481.12" b="N"/>
<point x="392.89" y="481.12" b="N"/>
<point x="405.13" y="481.12" b="N"/>
<point x="417.38" y="481.12" b="A"/>
<point x="429.62" y="481.12" b="A"/>
<point x="441.87" y="481.12" b="G"/>
<point x="454.12" y="481.12" b="G"/>
<point x="466.36" y="481.12" b="A"/>
<point x="478.61" y="481.12" b="G"/>
</structure>
